{
  "tardisSystem": [
    "time rotor",
    "helmic regulator",
    "atmospheric gauge dials",
    "emergency switch",
    "visual stabiliser circuit",
    "door control",
    "scanner switch",
    "fast return switch",
    "materialisation control",
    "master switch",
    "audio unit",
    "stasis control",
    "navigation system",
    "coordinate input system",
    "memory bank",
    "navigational lock",
    "power response subsystem",
    "materialisation indicator",
    "immobiliser circuit",
    "power booster controls"
    "dematerialisation control",
    "radiation detector",
    "absolute tesseractulator",
    "directional unit",
    "astrosextant rectifier",
    "molecular stabiliser",
    "low energy distributor subsystem",
    "fluid link",
    "mercury fluid link",
    "console stem",
    "atron mainframe",
    "transpower well",
    "recessive housing",
    "time column",
    "temporal balancing governor",
    "emergency transceiver module",
    "chameleon circuit",
    "telepathic induction circuit",
    "Jibbert cathocode troisième timepiece",
    "psycho-telemetric circuit",
    "power stacks",
    "light-speed overdrive",
    "temporal reactors",
    "thermo-couplings",
    "excitonic circuitry",
    "main spacetime element",
    "dematerialisation circuit"
    "fault locator",
    "architectural reconfiguration system",
    "fuel rod",
    "Eye of Harmony",
    "Vortex mutli-loop stabiliser",
    "dimensional gyroscope stabiliser",
    "time sensor",
    "gravity tractor beam",
    "HADS",
    "Hostile Action Displacement System",
    "Hostile Action Dispersal System",
    "mechanical panel",
    "engine release",
    "handbreak",
    "lockdown mechanism",
    "helm panel",
    "eyepiece scanner",
    "time rotor handbreak",
    "space-time throttle",
    "navigation panel",
    "directional pointer",
    "atom accelerator",
    "spatial location input keyboard",
    "diagnostic panel",
    "communiucations panel",
    "telephone",
    "fabrication panel",
    "harmonic generator",
    "fabrication dispenser",
    "wibbly lever",
    "time path indicator"
  ],

  "tardisRooms": [
    "console room",
    "lab",
    "power room",
    "secondary console room",
    "cloister room",
    "cloister",
    "butterfly room",
    "zero room",
    "ancillary power center",
    "swimming pool",
    "library",
    "wardrobe"
    "wardrobe room",
    "holding ring",
    "kitchen",
    "greenhouse",
    "garden",
    "aquarium",
    "zoo",
    "small library",
    "dimensional induction chamber",
    "tool shed",
    "boot cupbard",
    "garage",
    "art gallery",
    "drawing room",
    "LEGO room",
    "sick bay",
    "Storeroom 89",
    "Storeroom 90",
    "Storeroom 104",
    "Fourth Doctor's scarf room",
    "cricket club",
    "cricket pitch",
    "croquet court",
    "art studio",
    "television room",
    "time-space visualiser room",
    "observatory",
  ],

  "tardisMeans": [
    "Time And Relative Dimensions In Space. It means #tardisDesc#."
  ],

  "tardisDesc": [
    "life",
    "death",
    "what the hell",
    "good times",
    "bad times",
    "unlimited rice pudding",
    "blood",
    "time",
    "pain",
    "adventure",
    "fun",
    "other planets",
    "all of time and space",
    "TARDIS",
    "\\#vworpvworp",
    "dissapearing here, reappeaing there",
    "doom"
  ],

  "faultLocator": [
    "Fault Locator alert! There is a fault in the #tardisSystem#.",
    "Fault Locator reports the #tardisSystem# is #brokenSys#.",
    "Fault Locator alert! All systems functioning normally.",
    "Alert! Fault Locator reports the #tardisSystem# is #brokenSys#.",
    "Ding! Ding! Ding! There is a fault in the #tardisSystem#."
  ],

  "brokenSys:": [
    "broken",
    "busted",
    "kaput",
    "inoperative",
    "faulty",
    "damaged",
    "in need of service",
    "cracked",
    "defective",
    "fractured",
    "mangled",
    "ruptured",
    "severed"
  ],

  "tardisSyn": [
    "TARDIS",
    "Ship",
  ]
}
